{"a":"אחד","all":"כל","and":"ו","answer":"לענות","ask":"לשאול","at":"ב","bad":"רע","be":"להיות","beautiful":"יפה","big":"גדול","bird":"ציפור","book":"ספר","bread":"לחם","but":"אבל","buy":"לקנות","car":"מכונית","cat":"חתול","chair":"כיסא","child":"ילד","city":"עיר","close":"לסגור","coffee":"קפה","cold":"קר","come":"לבוא","computer":"מחשב","country":"ארץ","day":"יום","do":"לעשות","dog":"כלב","door":"דלת","drink":"לשתות","easy":"קל","eat":"לאכול","eight":"שמונה","evening":"ערב","excuse me":"סליחה","family":"משפחה","fast":"מהיר","find":"למצוא","first":"ראשון","fish":"דג","five":"חמש","flower":"פרח","food":"אוכל","for":"עבור","four":"ארבע","friday":"יום שישי","friend":"חבר","from":"מ","give":"לתת","go":"ללכת","good":"טוב","good morning":"בוקר טוב","good night":"לילה טוב","goodbye":"להתראות","happy":"שמח","hard":"קשה","have":"יש","he":"הוא","hear":"לשמוע","hello":"שלום","help":"לעזור","here":"כאן","home":"בית","hot":"חם","hour":"שעה","house":"בית","how":"איך","how are you":"מה שלומך","hundred":"מאה","i":"אני","i love you":"אני אוהב אותך","if":"אם","in":"ב","know":"לדעת","language":"שפה","last":"אחרון","life":"חיים","light":"אור","like":"לחבב","long":"ארוך","love":"אהבה","make":"ליצור","man":"איש","milk":"חלב","minute":"דקה","monday":"יום שני","money":"כסף","month":"חודש","moon":"ירח","morning":"בוקר","music":"מוזיקה","name":"שם","need":"להזדקק","new":"חדש","night":"לילה","nine":"תשע","no":"לא","not":"לא","now":"עכשיו","of":"של","old":"ישן","on":"על","one":"אחד","open":"לפתוח","or":"או","phone":"טלפון","please":"בבקשה","read":"לקרוא","right":"נכון","river":"נהר","road":"דרך","run":"לרוץ","sad":"עצוב","saturday":"שבת","school":"בית ספר","sea":"ים","see":"לראות","see you later":"נתראה","sell":"למכור","seven":"שבע","she":"היא","short":"קצר","six":"שש","sky":"שמיים","sleep":"לישון","slow":"איטי","small":"קטן","some":"כמה","sorry":"סליחה","speak":"לדבר","star":"כוכב","start":"להתחיל","stop":"לעצור","street":"רחוב","sun":"שמש","sunday":"יום ראשון","table":"שולחן","take":"לקחת","tea":"תה","ten":"עשר","thank you":"תודה","that":"ההוא","the":"ה","then":"אז","there":"שם","they":"הם","think":"לחשוב","this":"זה","thousand":"אלף","three":"שלוש","thursday":"יום חמישי","time":"זמן","to":"אל","today":"היום","tomorrow":"מחר","tree":"עץ","tuesday":"יום שלישי","two":"שתיים","walk":"ללכת","want":"לרצות","water":"מים","we":"אנחנו","wednesday":"יום רביעי","week":"שבוע","welcome":"ברוך הבא","what":"מה","when":"מתי","where":"איפה","who":"מי","why":"למה","window":"חלון","with":"עם","woman":"אישה","work":"עבודה","world":"עולם","write":"לכתוב","wrong":"שגוי","year":"שנה","yes":"כן","yesterday":"אתמול","you":"אתה"}
